fcaptcha/__init__.py
fcaptcha/exceptions.py
fcaptcha/fcaptcha.py
fcaptcha-0.0.3.dist-info/LICENSE.txt
fcaptcha-0.0.3.dist-info/METADATA
fcaptcha-0.0.3.dist-info/WHEEL
fcaptcha-0.0.3.dist-info/top_level.txt
fcaptcha-0.0.3.dist-info/RECORD
