Metadata-Version: 2.1
Name: fcaptcha
Version: 0.0.3
Summary: Official fCaptcha Wrapper
Home-page: https://github.com/fCaptcha/wrapper-py
Author: Body Alhoha
Author-email: bodyalhoha@gmail.com
License: MIT
Classifier: Programming Language :: Python :: 3
Classifier: License :: OSI Approved :: MIT License
Classifier: Operating System :: OS Independent
Requires-Python: >=3.6
License-File: LICENSE.txt
